Workbook

Sheet Summary
A1: CoinGecko_ID | B1: Name | C1: Symbol | D1: E | E1: S | F1: G | G1: TOTAL
A2: bitcoin | B2: Bitcoin | C2: BTC | D2: =_xlfn.XLOOKUP(C2,Sheet1!B:B,Sheet1!C:C) -> 0 | E2: =_xlfn.XLOOKUP(C2,Sheet1!B:B,Sheet1!D:D) -> 2 | F2: =_xlfn.XLOOKUP(C2,Sheet1!B:B,Sheet1!E:E) -> 1 | G2: =SUM(D2:F2) -> 3
A3: ethereum | B3: Ethereum | C3: ETH | D3: =_xlfn.XLOOKUP(C3,Sheet1!B:B,Sheet1!C:C) -> 1 | E3: =_xlfn.XLOOKUP(C3,Sheet1!B:B,Sheet1!D:D) -> 4 | F3: =_xlfn.XLOOKUP(C3,Sheet1!B:B,Sheet1!E:E) -> 1 | G3: =SUM(D3:F3) -> 6
A4: binancecoin | B4: BNB | C4: BNB | D4: =_xlfn.XLOOKUP(C4,Sheet1!B:B,Sheet1!C:C) -> 2 | E4: =_xlfn.XLOOKUP(C4,Sheet1!B:B,Sheet1!D:D) -> 4 | F4: =_xlfn.XLOOKUP(C4,Sheet1!B:B,Sheet1!E:E) -> 0 | G4: =SUM(D4:F4) -> 6
A5: solana | B5: Solana | C5: SOL | D5: =_xlfn.XLOOKUP(C5,Sheet1!B:B,Sheet1!C:C) -> 2 | E5: =_xlfn.XLOOKUP(C5,Sheet1!B:B,Sheet1!D:D) -> 4 | F5: =_xlfn.XLOOKUP(C5,Sheet1!B:B,Sheet1!E:E) -> 1 | G5: =SUM(D5:F5) -> 7
A6: cardano | B6: Cardano | C6: ADA | D6: =_xlfn.XLOOKUP(C6,Sheet1!B:B,Sheet1!C:C) -> 3 | E6: =_xlfn.XLOOKUP(C6,Sheet1!B:B,Sheet1!D:D) -> 6 | F6: =_xlfn.XLOOKUP(C6,Sheet1!B:B,Sheet1!E:E) -> 2 | G6: =SUM(D6:F6) -> 11
A7: polkadot | B7: Polkadot | C7: DOT | D7: =_xlfn.XLOOKUP(C7,Sheet1!B:B,Sheet1!C:C) -> 2 | E7: =_xlfn.XLOOKUP(C7,Sheet1!B:B,Sheet1!D:D) -> 4 | F7: =_xlfn.XLOOKUP(C7,Sheet1!B:B,Sheet1!E:E) -> 3 | G7: =SUM(D7:F7) -> 9
A8: avalanche-2 | B8: Avalanche | C8: AVAX | D8: =_xlfn.XLOOKUP(C8,Sheet1!B:B,Sheet1!C:C) -> 2 | E8: =_xlfn.XLOOKUP(C8,Sheet1!B:B,Sheet1!D:D) -> 4 | F8: =_xlfn.XLOOKUP(C8,Sheet1!B:B,Sheet1!E:E) -> 2 | G8: =SUM(D8:F8) -> 8
A9: cosmos | B9: Cosmos | C9: ATOM | D9: =_xlfn.XLOOKUP(C9,Sheet1!B:B,Sheet1!C:C) -> 2 | E9: =_xlfn.XLOOKUP(C9,Sheet1!B:B,Sheet1!D:D) -> 4 | F9: =_xlfn.XLOOKUP(C9,Sheet1!B:B,Sheet1!E:E) -> 2 | G9: =SUM(D9:F9) -> 8
A10: near | B10: NEAR | C10: NEAR | D10: =_xlfn.XLOOKUP(C10,Sheet1!B:B,Sheet1!C:C) -> 3 | E10: =_xlfn.XLOOKUP(C10,Sheet1!B:B,Sheet1!D:D) -> 6 | F10: =_xlfn.XLOOKUP(C10,Sheet1!B:B,Sheet1!E:E) -> 2 | G10: =SUM(D10:F10) -> 11
A11: algorand | B11: Algorand | C11: ALGO | D11: =_xlfn.XLOOKUP(C11,Sheet1!B:B,Sheet1!C:C) -> 3 | E11: =_xlfn.XLOOKUP(C11,Sheet1!B:B,Sheet1!D:D) -> 6 | F11: =_xlfn.XLOOKUP(C11,Sheet1!B:B,Sheet1!E:E) -> 2 | G11: =SUM(D11:F11) -> 11
A12: hedera-hashgraph | B12: Hedera | C12: HBAR | D12: =_xlfn.XLOOKUP(C12,Sheet1!B:B,Sheet1!C:C) -> 3 | E12: =_xlfn.XLOOKUP(C12,Sheet1!B:B,Sheet1!D:D) -> 6 | F12: =_xlfn.XLOOKUP(C12,Sheet1!B:B,Sheet1!E:E) -> 3 | G12: =SUM(D12:F12) -> 12
A13: tron | B13: TRON | C13: TRX | D13: =_xlfn.XLOOKUP(C13,Sheet1!B:B,Sheet1!C:C) -> 2 | E13: =_xlfn.XLOOKUP(C13,Sheet1!B:B,Sheet1!D:D) -> 4 | F13: =_xlfn.XLOOKUP(C13,Sheet1!B:B,Sheet1!E:E) -> 0 | G13: =SUM(D13:F13) -> 6
... A51: wormhole | B51: Wormhole | C51: W | D51: =_xlfn.XLOOKUP(C51,Sheet1!B:B,Sheet1!C:C) -> 1 | E51: =_xlfn.XLOOKUP(C51,Sheet1!B:B,Sheet1!D:D) -> 4 | F51: =_xlfn.XLOOKUP(C51,Sheet1!B:B,Sheet1!E:E) -> 2 | G51: =SUM(D51:F51) -> 7

Sheet Sheet1
A1: Asset | B1: Symbol | C1: Environment (0-3) | D1: Social (0-6) | E1: Governance (0-3)
A2: Cardano (ADA) | B2: =_xlfn.TEXTBEFORE(_xlfn.TEXTAFTER(A2,"("),")") -> ADA | C2: 3 | D2: 6 | E2: 2
A3: Stellar (XLM) | B3: =_xlfn.TEXTBEFORE(_xlfn.TEXTAFTER(A3,"("),")") -> XLM | C3: 3 | D3: 6 | E3: 3
A4: Polkadot (DOT) | B4: =_xlfn.TEXTBEFORE(_xlfn.TEXTAFTER(A4,"("),")") -> DOT | C4: 2 | D4: 4 | E4: 3
A5: Hedera (HBAR) | B5: =_xlfn.TEXTBEFORE(_xlfn.TEXTAFTER(A5,"("),")") -> HBAR | C5: 3 | D5: 6 | E5: 3
A6: Algorand (ALGO) | B6: =_xlfn.TEXTBEFORE(_xlfn.TEXTAFTER(A6,"("),")") -> ALGO | C6: 3 | D6: 6 | E6: 2
A7: Filecoin (FIL) | B7: =_xlfn.TEXTBEFORE(_xlfn.TEXTAFTER(A7,"("),")") -> FIL | C7: 3 | D7: 6 | E7: 2
A8: NEAR Protocol (NEAR) | B8: =_xlfn.TEXTBEFORE(_xlfn.TEXTAFTER(A8,"("),")") -> NEAR | C8: 3 | D8: 6 | E8: 2
A9: Chainlink (LINK) | B9: =_xlfn.TEXTBEFORE(_xlfn.TEXTAFTER(A9,"("),")") -> LINK | C9: 2 | D9: 6 | E9: 2
A10: Cosmos (ATOM) | B10: =_xlfn.TEXTBEFORE(_xlfn.TEXTAFTER(A10,"("),")") -> ATOM | C10: 2 | D10: 4 | E10: 2
A11: Avalanche (AVAX) | B11: =_xlfn.TEXTBEFORE(_xlfn.TEXTAFTER(A11,"("),")") -> AVAX | C11: 2 | D11: 4 | E11: 2
A12: Ethereum (ETH) | B12: =_xlfn.TEXTBEFORE(_xlfn.TEXTAFTER(A12,"("),")") -> ETH | C12: 1 | D12: 4 | E12: 1
A13: Solana (SOL) | B13: =_xlfn.TEXTBEFORE(_xlfn.TEXTAFTER(A13,"("),")") -> SOL | C13: 2 | D13: 4 | E13: 1
... A27: Arbitrum (ARB) | B27: =_xlfn.TEXTBEFORE(_xlfn.TEXTAFTER(A27,"("),")") -> ARB | C27: 2 | D27: 4 | E27: 2
A28: ENS | B28: ENS | C28: 1 | D28: 4 | E28: 3
A29: Wormhole (W) | B29: =_xlfn.TEXTBEFORE(_xlfn.TEXTAFTER(A29,"("),")") -> W | C29: 1 | D29: 4 | E29: 2
A30: The Graph (GRT) | B30: =_xlfn.TEXTBEFORE(_xlfn.TEXTAFTER(A30,"("),")") -> GRT | C30: 1 | D30: 4 | E30: 2
A31: dYdX (DYDX) | B31: =_xlfn.TEXTBEFORE(_xlfn.TEXTAFTER(A31,"("),")") -> DYDX | C31: 2 | D31: 4 | E31: 2
A32: GMX (GMX) | B32: =_xlfn.TEXTBEFORE(_xlfn.TEXTAFTER(A32,"("),")") -> GMX | C32: 2 | D32: 4 | E32: 2
A33: Pendle (PENDLE) | B33: =_xlfn.TEXTBEFORE(_xlfn.TEXTAFTER(A33,"("),")") -> PENDLE | C33: 1 | D33: 4 | E33: 2
A34: Yearn (YFI) | B34: =_xlfn.TEXTBEFORE(_xlfn.TEXTAFTER(A34,"("),")") -> YFI | C34: 1 | D34: 4 | E34: 2
A35: Maker (MKR) | B35: =_xlfn.TEXTBEFORE(_xlfn.TEXTAFTER(A35,"("),")") -> MKR | C35: 1 | D35: 4 | E35: 1
A36: Rocket Pool (rETH) | B36: =_xlfn.TEXTBEFORE(_xlfn.TEXTAFTER(A36,"("),")") -> rETH | C36: 1 | D36: 4 | E36: 3
A37: Lido (stETH) | B37: =_xlfn.TEXTBEFORE(_xlfn.TEXTAFTER(A37,"("),")") -> stETH | C37: 1 | D37: 4 | E37: 1
A38: Dai (DAI) | B38: =_xlfn.TEXTBEFORE(_xlfn.TEXTAFTER(A38,"("),")") -> DAI | C38: 1 | D38: 3 | E38: 2
A39: Frax (FRAX) | B39: =_xlfn.TEXTBEFORE(_xlfn.TEXTAFTER(A39,"("),")") -> FRAX | C39: 1 | D39: 3 | E39: 2
A40: USDC | B40: USDC | C40: 1 | D40: 3 | E40: 0
A41: USDT | B41: USDT | C41: 1 | D41: 3 | E41: 0
A42: FDUSD | B42: FDUSD | C42: 1 | D42: 3 | E42: 0
A43: PYUSD | B43: PYUSD | C43: 1 | D43: 3 | E43: 0
A44: Ondo (ONDO) | B44: =_xlfn.TEXTBEFORE(_xlfn.TEXTAFTER(A44,"("),")") -> ONDO | C44: 1 | D44: 2 | E44: 3
A45: Wrapped Bitcoin (WBTC) | B45: =_xlfn.TEXTBEFORE(_xlfn.TEXTAFTER(A45,"("),")") -> WBTC | C45: 0 | D45: 2 | E45: 0
A46: ApeCoin (APE) | B46: =_xlfn.TEXTBEFORE(_xlfn.TEXTAFTER(A46,"("),")") -> APE | C46: 1 | D46: 1 | E46: 2
A47: Decentraland (MANA) | B47: =_xlfn.TEXTBEFORE(_xlfn.TEXTAFTER(A47,"("),")") -> MANA | C47: 1 | D47: 1 | E47: 2
A48: The Sandbox (SAND) | B48: =_xlfn.TEXTBEFORE(_xlfn.TEXTAFTER(A48,"("),")") -> SAND | C48: 1 | D48: 1 | E48: 2
A49: Blur (BLUR) | B49: =_xlfn.TEXTBEFORE(_xlfn.TEXTAFTER(A49,"("),")") -> BLUR | C49: 1 | D49: 1 | E49: 2
A50: LooksRare (LOOKS) | B50: =_xlfn.TEXTBEFORE(_xlfn.TEXTAFTER(A50,"("),")") -> LOOKS | C50: 1 | D50: 1 | E50: 2
A51: Basic Attention (BAT) | B51: =_xlfn.TEXTBEFORE(_xlfn.TEXTAFTER(A51,"("),")") -> BAT | C51: 1 | D51: 1 | E51: 0

Sheet Governance
A1: Asset | B1: Name | C1: Legal (0-4) | D1: Protocol (0-4) | E1: Internal Control (0-2) | F1: Total (0-10) | G1: Rationale
A2: ADA | B2: Cardano | C2: 3 | D2: 4 | E2: 2 | F2: 9 | G2: Tripartite entities; On-chain Constitution; Transparent treasury.
A3: DOT | B3: Polkadot | C3: 3 | D3: 4 | E3: 2 | F3: 9 | G3: Swiss Foundation; OpenGov bicameral system; On-chain treasury.
A4: OP | B4: Optimism | C4: 3 | D4: 4 | E4: 2 | F4: 9 | G4: Bicameral (Token + Citizens' House); Cayman Foundation.
A5: ETH | B5: Ethereum | C5: 3 | D5: 3 | E5: 2 | F5: 8 | G5: Swiss Foundation; Robust off-chain consensus; Global audits.
A6: ATOM | B6: Cosmos | C6: 3 | D6: 3 | E6: 2 | F6: 8 | G6: Interchain Foundation; Active on-chain gov; Community pool.
A7: GRT | B7: The Graph | C7: 3 | D7: 3 | E7: 2 | F7: 8 | G7: Foundation; Representative Council (Multisig); Transparent grants.
A8: ARB | B8: Arbitrum | C8: 3 | D8: 3 | E8: 2 | F8: 8 | G8: Cayman Foundation; Elected Security Council; On-chain DAO.
A9: ONDO | B9: Ondo | C9: 4 | D9: 2 | E9: 2 | F9: 8 | G9: BVI SPV (Institutional); Permissioned gov; High audit freq.
A10: ENS | B10: ENS | C10: 3 | D10: 3 | E10: 2 | F10: 8 | G10: Cayman Foundation; Constitutionally bound delegates.
A11: DYDX | B11: dYdX | C11: 3 | D11: 3 | E11: 2 | F11: 8 | G11: Cayman Foundation; Fully decentralized v4 chain gov.
A12: UNI | B12: Uniswap | C12: 2 | D12: 3 | E12: 2 | F12: 7 | G12: Foundation + DAO (Uninc.); Huge treasury; VC delegation.
A13: AAVE | B13: Aave | C13: 2 | D13: 3 | E13: 2 | F13: 7 | G13: "Guardian" veto; Service provider elections; UK entities.
... A51: BAT | B51: Basic Attn | C51: 1 | D51: 0 | E51: 1 | F51: 2 | G51: Corporate product (Brave); No governance rights.

Sheet Environment
A1: CoinGecko_ID | B1: Name | C1: Type | D1: E1 | E1: E2 | F1: E3 | G1: Total | H1: Rationale & Key Citations
A2: bitcoin | B2: Bitcoin | C2: PoW | D2: 0 | E2: 0 | F2: 0 | G2: 0 | H2: 175 TWh/yr, 98 MtCO2e/yr. Massive ASIC waste.5
A3: ethereum | B3: Ethereum | C3: PoS | D3: 3 | E3: 4 | F3: 2 | G3: 9 | H3: ~5 GWh/yr. 99.99% reduction post-merge.12
A4: binancecoin | B4: BNB | C4: PoS | D4: 3 | E4: 4 | F4: 2 | G4: 9 | H4: ~0.11 GWh/yr. Highly efficient authority set.12
A5: solana | B5: Solana | C5: PoS | D5: 2 | E5: 3 | F5: 2 | G5: 7 | H5: ~14 GWh/yr. High hardware specs drive moderate use.14
A6: cardano | B6: Cardano | C6: PoS | D6: 3 | E6: 4 | F6: 2 | G6: 9 | H6: ~0.5 GWh/yr. Very efficient liquid staking.20
A7: polkadot | B7: Polkadot | C7: PoS | D7: 4 | E7: 4 | F7: 2 | G7: 10 | H7: ~70-140 MWh/yr. Lowest among major L1s.17
A8: avalanche-2 | B8: Avalanche | C8: PoS | D8: 3 | E8: 4 | F8: 2 | G8: 9 | H8: ~0.48 GWh/yr. Lightweight consensus.17
A9: cosmos | B9: Cosmos Hub | C9: PoS | D9: 4 | E9: 4 | F9: 2 | G9: 10 | H9: Low validator count limits total energy draw.32
A10: near | B10: NEAR Protocol | C10: PoS | D10: 4 | E10: 4 | F10: 2 | G10: 10 | H10: Certified Climate Neutral product.24
A11: algorand | B11: Algorand | C11: PoS | D11: 4 | E11: 4 | F11: 2 | G11: 10 | H11: Pure PoS designed for minimal energy (<100 MWh).33
A12: hedera-hashgraph | B12: Hedera | C12: DLT | D12: 4 | E12: 4 | F12: 2 | G12: 10 | H12: Hashgraph is exceptionally efficient (0.000003 kWh/tx).23
A13: tron | B13: TRON | C13: PoS | D13: 2 | E13: 3 | F13: 2 | G13: 7 | H13: ~3.4 GWh/yr. Higher usage than DOT/ADA.12
... A51: wormhole | B51: Wormhole | C51: Infra | D51: 4 | E51: 4 | F51: 2 | G51: 10 | H51: Guardian network has low node count.37

Sheet Social
A1: Rank | B1: Name | C1: Ticker | D1: Societal Impact (0-4) | E1: Investor Protection (0-4) | F1: Inclusivity (0-2) | G1: Total Score (0-10) | H1: Rationale Summary
A2: 1 | B2: Bitcoin | C2: BTC | D2: 4 | E2: 4 | F2: 2 | G2: 10 | H2: Global store of value; zero protocol hacks; highly decentralized.
A3: 2 | B3: USD Coin | C3: USDC | D3: 4 | E3: 4 | F3: 2 | G3: 10 | H3: Regulated, transparent reserves; high payment utility.28
A4: 3 | B4: Ethereum | C4: ETH | D4: 4 | E4: 3 | F4: 2 | G4: 9 | H4: Backbone of Web3; slight centralization in staking.15
A5: 4 | B5: PayPal USD | C5: PYUSD | D5: 4 | E5: 4 | F5: 1 | G5: 9 | H5: Massive mainstream access; centralized issuer (Paxos).26
A6: 5 | B6: Chainlink | C6: LINK | D6: 4 | E6: 4 | F6: 1 | G6: 9 | H6: Critical oracle infrastructure; secure but permissioned nodes.31
A7: 6 | B7: Litecoin | C7: LTC | D7: 3 | E7: 4 | F7: 2 | G7: 9 | H7: 100% uptime; commodity status; accessible mining.11
A8: 7 | B8: Uniswap | C8: UNI | D8: 4 | E8: 3 | F8: 2 | G8: 9 | H8: Top DEX; immutable contracts; regulatory friction.39
A9: 8 | B9: Aave | C9: AAVE | D9: 3 | E9: 4 | F9: 2 | G9: 9 | H9: Top lending protocol; high safety scores; open access.33
A10: 9 | B10: ENS | C10: ENS | D10: 3 | E10: 4 | F10: 2 | G10: 9 | H10: Key identity utility; strong DAO governance.
A11: 10 | B11: Cardano | C11: ADA | D11: 3 | E11: 3 | F11: 2 | G11: 8 | H11: Academic rigor; accessible staking; lower DeFi usage.21
A12: 11 | B12: Tether | C12: USDT | D12: 4 | E12: 2 | F12: 2 | G12: 8 | H12: Dominant liquidity; historical transparency concerns.30
A13: 12 | B13: Dai | C13: DAI | D13: 3 | E13: 3 | F13: 2 | G13: 8 | H13: Decentralized stablecoin; resilient governance.
... A51: 50 | B51: LooksRare | C51: LOOKS | D51: 1 | E51: 2 | F51: 2 | G51: 5 | H51: Wash trading dominance; low organic utility.
